LICENSE
MANIFEST.in
README.md
requirements.txt
setup.cfg
setup.py
linkedrw/__init__.py
linkedrw/__main__.py
linkedrw/constants.py
linkedrw/exceptions.py
linkedrw/main.py
linkedrw.egg-info/PKG-INFO
linkedrw.egg-info/SOURCES.txt
linkedrw.egg-info/dependency_links.txt
linkedrw.egg-info/entry_points.txt
linkedrw.egg-info/requires.txt
linkedrw.egg-info/top_level.txt
linkedrw/linkedr/__init__.py
linkedrw/linkedr/publication.py
linkedrw/linkedr/resume.py
linkedrw/linkedr/section.py
linkedrw/linkedr/skill.py
linkedrw/linkedw/__init__.py
linkedrw/linkedw/website.py
linkedrw/scraper/__init__.py
linkedrw/scraper/accomplishment.py
linkedrw/scraper/background.py
linkedrw/scraper/personal.py
linkedrw/scraper/scrape.py
linkedrw/templates/index_template.html
linkedrw/templates/resume_template.tex
linkedrw/templates/awesome_cv_files/awesome-cv.cls
linkedrw/templates/awesome_cv_files/fontawesome.sty
linkedrw/templates/awesome_cv_files/fonts/FontAwesome.ttf
linkedrw/templates/awesome_cv_files/fonts/Roboto-Bold.ttf
linkedrw/templates/awesome_cv_files/fonts/Roboto-BoldItalic.ttf
linkedrw/templates/awesome_cv_files/fonts/Roboto-Italic.ttf
linkedrw/templates/awesome_cv_files/fonts/Roboto-Light.ttf
linkedrw/templates/awesome_cv_files/fonts/Roboto-LightItalic.ttf
linkedrw/templates/awesome_cv_files/fonts/Roboto-Medium.ttf
linkedrw/templates/awesome_cv_files/fonts/Roboto-MediumItalic.ttf
linkedrw/templates/awesome_cv_files/fonts/Roboto-Regular.ttf
linkedrw/templates/awesome_cv_files/fonts/Roboto-Thin.ttf
linkedrw/templates/awesome_cv_files/fonts/Roboto-ThinItalic.ttf
linkedrw/templates/dev_portfolio_files/gulpfile.js
linkedrw/templates/dev_portfolio_files/package.json
linkedrw/templates/dev_portfolio_files/css/bootstrap.min.css
linkedrw/templates/dev_portfolio_files/css/styles.css
linkedrw/templates/dev_portfolio_files/images/lead-bg.jpg
linkedrw/templates/dev_portfolio_files/js/scripts.js
linkedrw/templates/dev_portfolio_files/js/scripts.min.js
linkedrw/templates/dev_portfolio_files/libs/font-awesome/css/font-awesome.css
linkedrw/templates/dev_portfolio_files/libs/font-awesome/css/font-awesome.min.css
linkedrw/templates/dev_portfolio_files/libs/font-awesome/fonts/FontAwesome.otf
