Metadata-Version: 2.1
Name: linkedrw
Version: 1.2.0
Summary: A simple CLI for you to create your resume and personal website based on your LinkedIn profile
Home-page: https://github.com/zeshuaro/LinkedRW
Author: Joshua Tang
Author-email: zeshuaro@gmail.com
License: MIT License
Keywords: python scraper cv resume portfolio profile website
Platform: UNKNOWN
Classifier: Development Status :: 5 - Production/Stable
Classifier: Intended Audience :: Developers
Classifier: License :: OSI Approved :: MIT License
Classifier: Operating System :: OS Independent
Classifier: Programming Language :: Python
Classifier: Programming Language :: Python :: 3.6
Classifier: Programming Language :: Python :: 3.7
Requires-Python: >=3.6
